quantumx/__init__.py
quantumx/analyze.py
quantumx/backup.py
quantumx/icon.ico
quantumx/interpreter.py
quantumx/post_install.py
quantumx/quantumx_builtins.py
quantumx/sample.py
quantumx-0.2.0.dist-info/LICENSE
quantumx-0.2.0.dist-info/METADATA
quantumx-0.2.0.dist-info/WHEEL
quantumx-0.2.0.dist-info/entry_points.txt
quantumx-0.2.0.dist-info/top_level.txt
quantumx-0.2.0.dist-info/RECORD
