Metadata-Version: 2.1
Name: quantumx
Version: 0.2.0
Summary: A quantum-inspired programming language
Home-page: https://github.com/dhanushs005/quantumx
Author: Dhanush Selvaraj
Author-email: sdhanush451@gmail.com
License: MIT
Classifier: Programming Language :: Python :: 3
Classifier: License :: OSI Approved :: MIT License
Classifier: Operating System :: OS Independent
Requires-Python: >=3.8
License-File: LICENSE
Requires-Dist: numpy >=1.20
Requires-Dist: pandas >=1.3.0
